README.md
license
setup.py
LibraCreditoPDF2.egg-info/PKG-INFO
LibraCreditoPDF2.egg-info/SOURCES.txt
LibraCreditoPDF2.egg-info/dependency_links.txt
LibraCreditoPDF2.egg-info/requires.txt
LibraCreditoPDF2.egg-info/top_level.txt
leitor_all/__init__.py
leitor_all/leitor_all.py