Metadata-Version: 2.1
Name: LibraCreditoPDF2
Version: 0.0.1
Summary: leitor de PDF extrato
Author: Matheus Nascimento
Author-email: Matheuskater02@outlook.com
License: MIT License
Keywords: leitor all
License-File: license
Requires-Dist: tabula
Requires-Dist: PyPDF2
Requires-Dist: pandas
Requires-Dist: pdfminer
Requires-Dist: pdfminer.six
Requires-Dist: jpype1
Requires-Dist: openpyxl
